README.md
setup.py
sylo/__init__.py
sylo/__main__.py
sylo/args.py
sylo/cmdline.py
sylo/definitions.py
sylo/display.py
sylo/models.py
sylo/sylo.py
sylo/sylo_logging.py
sylo/utils.py
sylo.egg-info/PKG-INFO
sylo.egg-info/SOURCES.txt
sylo.egg-info/dependency_links.txt
sylo.egg-info/entry_points.txt
sylo.egg-info/not-zip-safe
sylo.egg-info/requires.txt
sylo.egg-info/top_level.txt