Metadata-Version: 2.1
Name: sylo
Version: 2.5.4
Summary: SYLO Python Pomodoro Timer
Home-page: http://github.com/rob-parker-what/sylo
Author: rob-parker-what
Author-email: robparkerwhat.dev@gmail.com
License: MIT
Keywords: pomodoro tomato timer terminal pomodoro-timer productivity todo-list tasks to-do gtd
Platform: UNKNOWN
Classifier: Intended Audience :: Developers
Classifier: License :: OSI Approved :: MIT License
Classifier: Programming Language :: Python
Classifier: Topic :: Software Development
Classifier: Operating System :: Unix
Classifier: Operating System :: MacOS
Requires-Python: >=3.7
